notion_beta_ti/__init__.py
notion_beta_ti/api_client.py
notion_beta_ti/api_response.py
notion_beta_ti/configuration.py
notion_beta_ti/exceptions.py
notion_beta_ti/py.typed
notion_beta_ti/rest.py
notion_beta_ti/api/__init__.py
notion_beta_ti/api/blocks_api.py
notion_beta_ti/api/comments_api.py
notion_beta_ti/api/databases_api.py
notion_beta_ti/api/pages_api.py
notion_beta_ti/api/search_api.py
notion_beta_ti/api/users_api.py
notion_beta_ti/models/__init__.py
notion_beta_ti-0.0.1.dist-info/METADATA
notion_beta_ti-0.0.1.dist-info/WHEEL
notion_beta_ti-0.0.1.dist-info/top_level.txt
notion_beta_ti-0.0.1.dist-info/RECORD
